library/__init__.py
library/base_2022/cables/__init__.py
library/base_2022/cables/array_core_wind.yaml
library/base_2022/cables/export_core_wind.yaml
library/base_2022/project/config/__init__.py
library/base_2022/project/config/base_fixed_bottom_2022.yaml
library/base_2022/project/config/base_fixed_bottom_2022_floris_jensen.yaml
library/base_2022/project/config/base_fixed_bottom_2022_install.yaml
library/base_2022/project/config/base_fixed_bottom_2022_operations.yaml
library/base_2022/project/config/base_floating_2022.yaml
library/base_2022/project/config/base_floating_2022_floris_jensen.yaml
library/base_2022/project/config/base_floating_2022_install.yaml
library/base_2022/project/config/base_floating_2022_operations.yaml
library/base_2022/project/config/fixed_costs_2022.yaml
library/base_2022/project/plant/__init__.py
library/base_2022/project/plant/base_fixed_bottom_2022_layout.csv
library/base_2022/project/plant/base_floating_2022_layout.csv
library/base_2022/project/port/__init__.py
library/base_2022/project/port/port_116km.yaml
library/base_2022/project/port/port_139km.yaml
library/base_2022/substations/__init__.py
library/base_2022/substations/offshore_substation_core_wind.yaml
library/base_2022/substructures/__init__.py
library/base_2022/turbines/12MW_216_RWT.csv
library/base_2022/turbines/12MW_216m.yaml
library/base_2022/turbines/12MW_core_wind.yaml
library/base_2022/turbines/12MW_core_wind_floating.yaml
library/base_2022/turbines/__init__.py
library/base_2022/vessels/__init__.py
library/base_2022/vessels/ahv.yaml
library/base_2022/vessels/clv.yaml
library/base_2022/vessels/ctv1.yaml
library/base_2022/vessels/ctv2.yaml
library/base_2022/vessels/ctv3.yaml
library/base_2022/vessels/ctv4.yaml
library/base_2022/vessels/ctv5.yaml
library/base_2022/vessels/ctv6.yaml
library/base_2022/vessels/ctv7.yaml
library/base_2022/vessels/demand_adjusted_cable_lay_vessel.yaml
library/base_2022/vessels/demand_adjusted_feeder_vessel.yaml
waves-0.6.1.dist-info/licenses/LICENSE
waves-0.6.1.dist-info/licenses/NOTICE
waves-0.6.1.dist-info/METADATA
waves-0.6.1.dist-info/WHEEL
waves-0.6.1.dist-info/entry_points.txt
waves-0.6.1.dist-info/top_level.txt
waves-0.6.1.dist-info/RECORD
