Metadata-Version: 2.4
Name: WAVES
Version: 0.6.1
Summary: Wind Asset Value Estimation System
Author-email: Rob Hammond <rob.hammond@nrel.gov>
License:                                  Apache License
Project-URL: source, https://github.com/NREL/WAVES
Project-URL: documentation, https://nrel.github.io/WAVES/
Project-URL: issues, https://github.com/NREL/WAVES/issues
Project-URL: changelog, https://github.com/NREL/WAVES/blob/main/CHANGELOG.md
Keywords: python3,wind-energy,operations-maintenance,operations-and-maintenance,balance-of-system,levelized-cost-of-energy,lcoe,aep,wakes,wake-analysis,energy-production,discrete-event-simulation,simulation
Classifier: Development Status :: 4 - Beta
Classifier: Intended Audience :: Science/Research
Classifier: License :: OSI Approved :: Apache Software License
Classifier: Natural Language :: English
Classifier: Operating System :: OS Independent
Classifier: Programming Language :: Python
Classifier: Programming Language :: Python :: 3 :: Only
Classifier: Programming Language :: Python :: 3.9
Classifier: Programming Language :: Python :: 3.10
Classifier: Topic :: Scientific/Engineering
Classifier: Topic :: Software Development :: Libraries :: Python Modules
Classifier: Typing :: Typed
Requires-Python: >=3.10
License-File: LICENSE
License-File: NOTICE
Requires-Dist: wombat>=0.11
Requires-Dist: orbit-nrel>=1.2.1
Requires-Dist: floris>=4.2.2
Requires-Dist: NREL-landbosse
Requires-Dist: tqdm
Requires-Dist: attrs
Requires-Dist: pyyaml
Requires-Dist: matplotlib>=3.6
Requires-Dist: numpy-financial>=1.0.0
Requires-Dist: typer>=0.12.3
Provides-Extra: dev
Requires-Dist: pre-commit; extra == "dev"
Requires-Dist: black; extra == "dev"
Requires-Dist: isort; extra == "dev"
Requires-Dist: pytest; extra == "dev"
Requires-Dist: pytest-cov; extra == "dev"
Requires-Dist: mypy; extra == "dev"
Requires-Dist: ruff; extra == "dev"
Provides-Extra: docs
Requires-Dist: jupyter-book; extra == "docs"
Requires-Dist: myst-nb; extra == "docs"
Requires-Dist: myst-parser; extra == "docs"
Requires-Dist: sphinx-autodoc-typehints; extra == "docs"
Requires-Dist: sphinxcontrib-autoyaml; extra == "docs"
Provides-Extra: examples
Requires-Dist: jupyterlab; extra == "examples"
Requires-Dist: jupyterlab-myst; extra == "examples"
Provides-Extra: all
Requires-Dist: waves[dev,docs,examples]; extra == "all"
Dynamic: license-file
